resiliparse/cli.py
resiliparse/itertools.cp39-win_amd64.pyd
resiliparse/__init__.py
resiliparse/beam/coders.py
resiliparse/beam/elasticsearch.py
resiliparse/beam/fileio.py
resiliparse/beam/textio.py
resiliparse/beam/warcio.py
resiliparse/beam/__init__.py
resiliparse/extract/html2text.cp39-win_amd64.pyd
resiliparse/extract/__init__.py
resiliparse/parse/encoding.cp39-win_amd64.pyd
resiliparse/parse/html.cp39-win_amd64.pyd
resiliparse/parse/http.cp39-win_amd64.pyd
resiliparse/parse/lang.cp39-win_amd64.pyd
resiliparse/parse/__init__.py
resiliparse-0.15.2.dist-info/DELVEWHEEL
resiliparse-0.15.2.dist-info/entry_points.txt
resiliparse-0.15.2.dist-info/METADATA
resiliparse-0.15.2.dist-info/RECORD
resiliparse-0.15.2.dist-info/top_level.txt
resiliparse-0.15.2.dist-info/WHEEL
resiliparse.libs/.load-order-resiliparse-0.15.2
resiliparse.libs/lexbor-e212d94906ddcd16804ac2f9b338964d.dll
resiliparse.libs/msvcp140-13abfb425c36116d4db3121c6c0c1aff.dll
resiliparse.libs/re2-fdb09800158e174e510c1e76d0407d66.dll
resiliparse.libs/uchardet-78688abdd6d63e46849eb52e688d8d2f.dll
