Metadata-Version: 2.1
Name: Resiliparse
Version: 0.15.2
Summary: A collection of robust and fast processing tools for parsing and analyzing (not only) web archive data.
Author: Janek Bevendorff
License: Apache License 2.0
Project-URL: repository, https://github.com/chatnoir-eu/chatnoir-resiliparse
Project-URL: homepage, https://resiliparse.chatnoir.eu
Project-URL: documentation, https://resiliparse.chatnoir.eu
Requires-Python: >=3.8
Requires-Dist: fastwarc ==0.15.2
Provides-Extra: all
Requires-Dist: resiliparse[beam,cli] ; extra == 'all'
Provides-Extra: beam
Requires-Dist: boto3 >=1.9 ; extra == 'beam'
Requires-Dist: elasticsearch >=7.0.0 ; extra == 'beam'
Requires-Dist: apache-beam[aws] >=2.37.0 ; (python_version < "3.12") and extra == 'beam'
Provides-Extra: cli
Requires-Dist: click ; extra == 'cli'
Requires-Dist: joblib ; extra == 'cli'
Requires-Dist: tqdm ; extra == 'cli'
Provides-Extra: cli-benchmark
Requires-Dist: beautifulsoup4 ; extra == 'cli-benchmark'
Requires-Dist: langid ; extra == 'cli-benchmark'
Requires-Dist: selectolax ; extra == 'cli-benchmark'
Provides-Extra: test
Requires-Dist: pytest >=7.2.2 ; extra == 'test'
Requires-Dist: pytest-cov >=4.0.0 ; extra == 'test'
